streamlit_autocomplete/__init__.py
streamlit_autocomplete/autocomplete.py
streamlit_autocomplete-0.1.0.dist-info/METADATA
streamlit_autocomplete-0.1.0.dist-info/WHEEL
streamlit_autocomplete-0.1.0.dist-info/top_level.txt
streamlit_autocomplete-0.1.0.dist-info/RECORD
