Metadata-Version: 2.4
Name: streamlit-autocomplete
Version: 0.1.0
Summary: Streamlit text_area autocomplete using streamlit-textcomplete
Author-email: Shrajal <shrajaljain3@gmail.com>
License: MIT
Project-URL: Homepage, https://github.com/Shrajal333/streamlit_autocomplete
Requires-Python: >=3.10.12
Requires-Dist: streamlit>=1.46.1
Requires-Dist: streamlit-textcomplete>=0.2.0
